fbruch/__init__.py
fbruch/utils.py
fbruch-1.0.2.dist-info/LICENSE
fbruch-1.0.2.dist-info/METADATA
fbruch-1.0.2.dist-info/WHEEL
fbruch-1.0.2.dist-info/entry_points.txt
fbruch-1.0.2.dist-info/top_level.txt
fbruch-1.0.2.dist-info/RECORD
