Metadata-Version: 2.1
Name: fbruch
Version: 1.0.2
Summary: Simple python library using graph api and scraping.
Home-page: https://github.com/jepluk/fbruch
Author: Errucha (jepluk)
Keywords: fb,facebook,fb-api,facebook-api,facebook-graph,bruteforce,facebook-scraping,fb-scraping,scraping
Classifier: Programming Language :: Python :: 3
Classifier: License :: OSI Approved :: MIT License
Classifier: Operating System :: OS Independent
License-File: LICENSE
Requires-Dist: requests
Requires-Dist: bs4
Requires-Dist: fake-useragent
